LICENSE
MANIFEST.in
README.md
setup.py
bfseg/__init__.py
bfseg/findmax.py
bfseg/watershed.py
bfseg.egg-info/PKG-INFO
bfseg.egg-info/SOURCES.txt
bfseg.egg-info/dependency_links.txt
bfseg.egg-info/top_level.txt
data/test.tif